LICENSE
README.md
setup.py
nertivia4py/__init__.py
nertivia4py/bot.py
nertivia4py.egg-info/PKG-INFO
nertivia4py.egg-info/SOURCES.txt
nertivia4py.egg-info/dependency_links.txt
nertivia4py.egg-info/requires.txt
nertivia4py.egg-info/top_level.txt
nertivia4py/commands/__init__.py
nertivia4py/commands/cog.py
nertivia4py/commands/command.py
nertivia4py/gateway/__init__.py
nertivia4py/gateway/events.py
nertivia4py/utils/__init__.py
nertivia4py/utils/bot.py
nertivia4py/utils/button.py
nertivia4py/utils/colour.py
nertivia4py/utils/dmchannel.py
nertivia4py/utils/embed.py
nertivia4py/utils/exceptions.py
nertivia4py/utils/extra.py
nertivia4py/utils/get.py
nertivia4py/utils/member.py
nertivia4py/utils/message.py
nertivia4py/utils/server.py
nertivia4py/utils/textchannel.py
nertivia4py/utils/user.py