Metadata-Version: 2.1
Name: nertivia4py
Version: 1.0.8
Summary: A Python wrapper for the Nertivia API
Home-page: https://github.com/bentettmar/nertivia4py
Author: Ben Tettmar
Author-email: hello@benny.fun
License: MIT
Keywords: nertivia,api,wrapper,python,bot,nertivia.py,nertivia4py
Platform: UNKNOWN
License-File: LICENSE
